{
  "id": "cfd73b5d-ae44-4320-8bee-de4760a48800",
  "prevId": "569d48a4-be56-4200-aa87-f946e9bf7b3b",
  "version": "7",
  "dialect": "postgresql",
  "tables": {
    "public.admins": {
      "name": "admins",
      "schema": "",
      "columns": {
        "id": {
          "name": "id",
          "type": "serial",
          "primaryKey": true,
          "notNull": true
        },
        "name": {
          "name": "name",
          "type": "text",
          "primaryKey": false,
          "notNull": true
        },
        "email": {
          "name": "email",
          "type": "text",
          "primaryKey": false,
          "notNull": true
        },
        "password": {
          "name": "password",
          "type": "text",
          "primaryKey": false,
          "notNull": true
        },
        "profile_picture": {
          "name": "profile_picture",
          "type": "text",
          "primaryKey": false,
          "notNull": false
        },
        "status": {
          "name": "status",
          "type": "varchar(20)",
          "primaryKey": false,
          "notNull": false,
          "default": "'active'"
        },
        "created_by": {
          "name": "created_by",
          "type": "integer",
          "primaryKey": false,
          "notNull": false
        },
        "created_at": {
          "name": "created_at",
          "type": "timestamp",
          "primaryKey": false,
          "notNull": false,
          "default": "now()"
        },
        "updated_at": {
          "name": "updated_at",
          "type": "timestamp",
          "primaryKey": false,
          "notNull": false,
          "default": "now()"
        },
        "last_login_at": {
          "name": "last_login_at",
          "type": "timestamp",
          "primaryKey": false,
          "notNull": false
        }
      },
      "indexes": {},
      "foreignKeys": {},
      "compositePrimaryKeys": {},
      "uniqueConstraints": {
        "admins_email_unique": {
          "name": "admins_email_unique",
          "nullsNotDistinct": false,
          "columns": [
            "email"
          ]
        }
      },
      "policies": {},
      "checkConstraints": {},
      "isRLSEnabled": false
    },
    "public.clients": {
      "name": "clients",
      "schema": "",
      "columns": {
        "id": {
          "name": "id",
          "type": "serial",
          "primaryKey": true,
          "notNull": true
        },
        "name": {
          "name": "name",
          "type": "text",
          "primaryKey": false,
          "notNull": true
        },
        "email": {
          "name": "email",
          "type": "text",
          "primaryKey": false,
          "notNull": true
        },
        "phone": {
          "name": "phone",
          "type": "varchar(20)",
          "primaryKey": false,
          "notNull": false
        },
        "password": {
          "name": "password",
          "type": "text",
          "primaryKey": false,
          "notNull": false
        },
        "google_id": {
          "name": "google_id",
          "type": "text",
          "primaryKey": false,
          "notNull": false
        },
        "apple_id": {
          "name": "apple_id",
          "type": "text",
          "primaryKey": false,
          "notNull": false
        },
        "microsoft_id": {
          "name": "microsoft_id",
          "type": "text",
          "primaryKey": false,
          "notNull": false
        },
        "auth_provider": {
          "name": "auth_provider",
          "type": "varchar(20)",
          "primaryKey": false,
          "notNull": false,
          "default": "'email'"
        },
        "reset_password_token": {
          "name": "reset_password_token",
          "type": "text",
          "primaryKey": false,
          "notNull": false
        },
        "reset_password_expiry": {
          "name": "reset_password_expiry",
          "type": "timestamp",
          "primaryKey": false,
          "notNull": false
        },
        "profile_picture": {
          "name": "profile_picture",
          "type": "text",
          "primaryKey": false,
          "notNull": false
        },
        "company_name": {
          "name": "company_name",
          "type": "text",
          "primaryKey": false,
          "notNull": false
        },
        "company_website": {
          "name": "company_website",
          "type": "text",
          "primaryKey": false,
          "notNull": false
        },
        "industry": {
          "name": "industry",
          "type": "varchar(100)",
          "primaryKey": false,
          "notNull": false
        },
        "address": {
          "name": "address",
          "type": "text",
          "primaryKey": false,
          "notNull": false
        },
        "city": {
          "name": "city",
          "type": "varchar(100)",
          "primaryKey": false,
          "notNull": false
        },
        "country": {
          "name": "country",
          "type": "varchar(100)",
          "primaryKey": false,
          "notNull": false
        },
        "tax_id": {
          "name": "tax_id",
          "type": "varchar(50)",
          "primaryKey": false,
          "notNull": false
        },
        "billing_address": {
          "name": "billing_address",
          "type": "text",
          "primaryKey": false,
          "notNull": false
        },
        "is_email_verified": {
          "name": "is_email_verified",
          "type": "boolean",
          "primaryKey": false,
          "notNull": false,
          "default": false
        },
        "is_phone_verified": {
          "name": "is_phone_verified",
          "type": "boolean",
          "primaryKey": false,
          "notNull": false,
          "default": false
        },
        "status": {
          "name": "status",
          "type": "varchar(20)",
          "primaryKey": false,
          "notNull": false,
          "default": "'active'"
        },
        "created_at": {
          "name": "created_at",
          "type": "timestamp",
          "primaryKey": false,
          "notNull": false,
          "default": "now()"
        },
        "updated_at": {
          "name": "updated_at",
          "type": "timestamp",
          "primaryKey": false,
          "notNull": false,
          "default": "now()"
        },
        "last_login_at": {
          "name": "last_login_at",
          "type": "timestamp",
          "primaryKey": false,
          "notNull": false
        }
      },
      "indexes": {},
      "foreignKeys": {},
      "compositePrimaryKeys": {},
      "uniqueConstraints": {
        "clients_email_unique": {
          "name": "clients_email_unique",
          "nullsNotDistinct": false,
          "columns": [
            "email"
          ]
        },
        "clients_google_id_unique": {
          "name": "clients_google_id_unique",
          "nullsNotDistinct": false,
          "columns": [
            "google_id"
          ]
        },
        "clients_apple_id_unique": {
          "name": "clients_apple_id_unique",
          "nullsNotDistinct": false,
          "columns": [
            "apple_id"
          ]
        },
        "clients_microsoft_id_unique": {
          "name": "clients_microsoft_id_unique",
          "nullsNotDistinct": false,
          "columns": [
            "microsoft_id"
          ]
        }
      },
      "policies": {},
      "checkConstraints": {},
      "isRLSEnabled": false
    },
    "public.developer_payments": {
      "name": "developer_payments",
      "schema": "",
      "columns": {
        "id": {
          "name": "id",
          "type": "serial",
          "primaryKey": true,
          "notNull": true
        },
        "developer_id": {
          "name": "developer_id",
          "type": "integer",
          "primaryKey": false,
          "notNull": true
        },
        "order_id": {
          "name": "order_id",
          "type": "varchar(100)",
          "primaryKey": false,
          "notNull": false
        },
        "payment_id": {
          "name": "payment_id",
          "type": "varchar(100)",
          "primaryKey": false,
          "notNull": false
        },
        "plan": {
          "name": "plan",
          "type": "varchar(20)",
          "primaryKey": false,
          "notNull": false
        },
        "billing_cycle": {
          "name": "billing_cycle",
          "type": "varchar(20)",
          "primaryKey": false,
          "notNull": false
        },
        "amount": {
          "name": "amount",
          "type": "integer",
          "primaryKey": false,
          "notNull": false
        },
        "currency": {
          "name": "currency",
          "type": "varchar(10)",
          "primaryKey": false,
          "notNull": false,
          "default": "'USD'"
        },
        "status": {
          "name": "status",
          "type": "varchar(20)",
          "primaryKey": false,
          "notNull": false,
          "default": "'created'"
        },
        "created_at": {
          "name": "created_at",
          "type": "timestamp",
          "primaryKey": false,
          "notNull": false,
          "default": "now()"
        },
        "completed_at": {
          "name": "completed_at",
          "type": "timestamp",
          "primaryKey": false,
          "notNull": false
        }
      },
      "indexes": {},
      "foreignKeys": {
        "developer_payments_developer_id_developers_id_fk": {
          "name": "developer_payments_developer_id_developers_id_fk",
          "tableFrom": "developer_payments",
          "tableTo": "developers",
          "columnsFrom": [
            "developer_id"
          ],
          "columnsTo": [
            "id"
          ],
          "onDelete": "no action",
          "onUpdate": "no action"
        }
      },
      "compositePrimaryKeys": {},
      "uniqueConstraints": {},
      "policies": {},
      "checkConstraints": {},
      "isRLSEnabled": false
    },
    "public.developer_products": {
      "name": "developer_products",
      "schema": "",
      "columns": {
        "id": {
          "name": "id",
          "type": "serial",
          "primaryKey": true,
          "notNull": true
        },
        "developer_id": {
          "name": "developer_id",
          "type": "integer",
          "primaryKey": false,
          "notNull": true
        },
        "project_id": {
          "name": "project_id",
          "type": "varchar(120)",
          "primaryKey": false,
          "notNull": true
        },
        "slug": {
          "name": "slug",
          "type": "varchar(160)",
          "primaryKey": false,
          "notNull": true
        },
        "name": {
          "name": "name",
          "type": "text",
          "primaryKey": false,
          "notNull": true
        },
        "product_category": {
          "name": "product_category",
          "type": "text",
          "primaryKey": false,
          "notNull": false
        },
        "tagline": {
          "name": "tagline",
          "type": "text",
          "primaryKey": false,
          "notNull": false
        },
        "short_description": {
          "name": "short_description",
          "type": "text",
          "primaryKey": false,
          "notNull": false
        },
        "problem": {
          "name": "problem",
          "type": "text",
          "primaryKey": false,
          "notNull": false
        },
        "solution": {
          "name": "solution",
          "type": "text",
          "primaryKey": false,
          "notNull": false
        },
        "features_tagline": {
          "name": "features_tagline",
          "type": "text",
          "primaryKey": false,
          "notNull": false
        },
        "features_about_body": {
          "name": "features_about_body",
          "type": "text",
          "primaryKey": false,
          "notNull": false
        },
        "benefits": {
          "name": "benefits",
          "type": "text",
          "primaryKey": false,
          "notNull": false
        },
        "features": {
          "name": "features",
          "type": "text",
          "primaryKey": false,
          "notNull": false
        },
        "use_cases": {
          "name": "use_cases",
          "type": "text",
          "primaryKey": false,
          "notNull": false
        },
        "audience_tags": {
          "name": "audience_tags",
          "type": "text",
          "primaryKey": false,
          "notNull": false
        },
        "customization_tiers": {
          "name": "customization_tiers",
          "type": "text",
          "primaryKey": false,
          "notNull": false
        },
        "trial_days": {
          "name": "trial_days",
          "type": "integer",
          "primaryKey": false,
          "notNull": false,
          "default": 0
        },
        "free_trial": {
          "name": "free_trial",
          "type": "boolean",
          "primaryKey": false,
          "notNull": false,
          "default": false
        },
        "deployment_time": {
          "name": "deployment_time",
          "type": "text",
          "primaryKey": false,
          "notNull": false
        },
        "best_for": {
          "name": "best_for",
          "type": "text",
          "primaryKey": false,
          "notNull": false
        },
        "technical_stack": {
          "name": "technical_stack",
          "type": "text",
          "primaryKey": false,
          "notNull": false
        },
        "technical_deployment": {
          "name": "technical_deployment",
          "type": "text",
          "primaryKey": false,
          "notNull": false
        },
        "technical_integrations": {
          "name": "technical_integrations",
          "type": "text",
          "primaryKey": false,
          "notNull": false
        },
        "technical_platforms": {
          "name": "technical_platforms",
          "type": "text",
          "primaryKey": false,
          "notNull": false
        },
        "technical_api": {
          "name": "technical_api",
          "type": "text",
          "primaryKey": false,
          "notNull": false
        },
        "technical_security": {
          "name": "technical_security",
          "type": "text",
          "primaryKey": false,
          "notNull": false
        },
        "technical_compliance": {
          "name": "technical_compliance",
          "type": "text",
          "primaryKey": false,
          "notNull": false
        },
        "icon_url": {
          "name": "icon_url",
          "type": "text",
          "primaryKey": false,
          "notNull": false
        },
        "screenshot_urls": {
          "name": "screenshot_urls",
          "type": "text",
          "primaryKey": false,
          "notNull": false
        },
        "demo_url": {
          "name": "demo_url",
          "type": "text",
          "primaryKey": false,
          "notNull": false
        },
        "demo_user": {
          "name": "demo_user",
          "type": "text",
          "primaryKey": false,
          "notNull": false
        },
        "demo_password": {
          "name": "demo_password",
          "type": "text",
          "primaryKey": false,
          "notNull": false
        },
        "demo_video_id": {
          "name": "demo_video_id",
          "type": "text",
          "primaryKey": false,
          "notNull": false
        },
        "support_docs": {
          "name": "support_docs",
          "type": "text",
          "primaryKey": false,
          "notNull": false
        },
        "support_email": {
          "name": "support_email",
          "type": "text",
          "primaryKey": false,
          "notNull": false
        },
        "support_chat": {
          "name": "support_chat",
          "type": "text",
          "primaryKey": false,
          "notNull": false
        },
        "support_response": {
          "name": "support_response",
          "type": "text",
          "primaryKey": false,
          "notNull": false
        },
        "legal_privacy": {
          "name": "legal_privacy",
          "type": "text",
          "primaryKey": false,
          "notNull": false
        },
        "legal_terms": {
          "name": "legal_terms",
          "type": "text",
          "primaryKey": false,
          "notNull": false
        },
        "legal_refund": {
          "name": "legal_refund",
          "type": "text",
          "primaryKey": false,
          "notNull": false
        },
        "marketplace_customization": {
          "name": "marketplace_customization",
          "type": "boolean",
          "primaryKey": false,
          "notNull": false,
          "default": true
        },
        "marketplace_white_label": {
          "name": "marketplace_white_label",
          "type": "boolean",
          "primaryKey": false,
          "notNull": false,
          "default": false
        },
        "marketplace_deployment_support": {
          "name": "marketplace_deployment_support",
          "type": "boolean",
          "primaryKey": false,
          "notNull": false,
          "default": false
        },
        "marketplace_onboarding_support": {
          "name": "marketplace_onboarding_support",
          "type": "boolean",
          "primaryKey": false,
          "notNull": false,
          "default": false
        },
        "meta_version": {
          "name": "meta_version",
          "type": "text",
          "primaryKey": false,
          "notNull": false
        },
        "meta_release_notes_url": {
          "name": "meta_release_notes_url",
          "type": "text",
          "primaryKey": false,
          "notNull": false
        },
        "meta_setup_time": {
          "name": "meta_setup_time",
          "type": "text",
          "primaryKey": false,
          "notNull": false
        },
        "meta_difficulty": {
          "name": "meta_difficulty",
          "type": "text",
          "primaryKey": false,
          "notNull": false
        },
        "meta_requirements": {
          "name": "meta_requirements",
          "type": "text",
          "primaryKey": false,
          "notNull": false
        },
        "trust_verified_listing": {
          "name": "trust_verified_listing",
          "type": "boolean",
          "primaryKey": false,
          "notNull": false,
          "default": false
        },
        "trust_verified_by_platform": {
          "name": "trust_verified_by_platform",
          "type": "boolean",
          "primaryKey": false,
          "notNull": false,
          "default": false
        },
        "trust_yoursaas_certified": {
          "name": "trust_yoursaas_certified",
          "type": "boolean",
          "primaryKey": false,
          "notNull": false,
          "default": false
        },
        "listing_status": {
          "name": "listing_status",
          "type": "varchar(20)",
          "primaryKey": false,
          "notNull": false,
          "default": "'draft'"
        },
        "created_at": {
          "name": "created_at",
          "type": "timestamp",
          "primaryKey": false,
          "notNull": false,
          "default": "now()"
        },
        "updated_at": {
          "name": "updated_at",
          "type": "timestamp",
          "primaryKey": false,
          "notNull": false,
          "default": "now()"
        }
      },
      "indexes": {},
      "foreignKeys": {
        "developer_products_developer_id_developers_id_fk": {
          "name": "developer_products_developer_id_developers_id_fk",
          "tableFrom": "developer_products",
          "tableTo": "developers",
          "columnsFrom": [
            "developer_id"
          ],
          "columnsTo": [
            "id"
          ],
          "onDelete": "no action",
          "onUpdate": "no action"
        }
      },
      "compositePrimaryKeys": {},
      "uniqueConstraints": {
        "developer_products_slug_unique": {
          "name": "developer_products_slug_unique",
          "nullsNotDistinct": false,
          "columns": [
            "slug"
          ]
        }
      },
      "policies": {},
      "checkConstraints": {},
      "isRLSEnabled": false
    },
    "public.developers": {
      "name": "developers",
      "schema": "",
      "columns": {
        "id": {
          "name": "id",
          "type": "serial",
          "primaryKey": true,
          "notNull": true
        },
        "name": {
          "name": "name",
          "type": "text",
          "primaryKey": false,
          "notNull": true
        },
        "email": {
          "name": "email",
          "type": "text",
          "primaryKey": false,
          "notNull": true
        },
        "phone": {
          "name": "phone",
          "type": "varchar(20)",
          "primaryKey": false,
          "notNull": false
        },
        "password": {
          "name": "password",
          "type": "text",
          "primaryKey": false,
          "notNull": false
        },
        "google_id": {
          "name": "google_id",
          "type": "text",
          "primaryKey": false,
          "notNull": false
        },
        "apple_id": {
          "name": "apple_id",
          "type": "text",
          "primaryKey": false,
          "notNull": false
        },
        "microsoft_id": {
          "name": "microsoft_id",
          "type": "text",
          "primaryKey": false,
          "notNull": false
        },
        "auth_provider": {
          "name": "auth_provider",
          "type": "varchar(20)",
          "primaryKey": false,
          "notNull": false,
          "default": "'email'"
        },
        "reset_password_token": {
          "name": "reset_password_token",
          "type": "text",
          "primaryKey": false,
          "notNull": false
        },
        "reset_password_expiry": {
          "name": "reset_password_expiry",
          "type": "timestamp",
          "primaryKey": false,
          "notNull": false
        },
        "profile_picture": {
          "name": "profile_picture",
          "type": "text",
          "primaryKey": false,
          "notNull": false
        },
        "cover_picture": {
          "name": "cover_picture",
          "type": "text",
          "primaryKey": false,
          "notNull": false
        },
        "bio": {
          "name": "bio",
          "type": "text",
          "primaryKey": false,
          "notNull": false
        },
        "skills": {
          "name": "skills",
          "type": "text",
          "primaryKey": false,
          "notNull": false
        },
        "experience": {
          "name": "experience",
          "type": "integer",
          "primaryKey": false,
          "notNull": false
        },
        "portfolio_url": {
          "name": "portfolio_url",
          "type": "text",
          "primaryKey": false,
          "notNull": false
        },
        "github_url": {
          "name": "github_url",
          "type": "text",
          "primaryKey": false,
          "notNull": false
        },
        "linkedin_url": {
          "name": "linkedin_url",
          "type": "text",
          "primaryKey": false,
          "notNull": false
        },
        "twitter_url": {
          "name": "twitter_url",
          "type": "text",
          "primaryKey": false,
          "notNull": false
        },
        "resume_url": {
          "name": "resume_url",
          "type": "text",
          "primaryKey": false,
          "notNull": false
        },
        "headline": {
          "name": "headline",
          "type": "text",
          "primaryKey": false,
          "notNull": false
        },
        "location": {
          "name": "location",
          "type": "varchar(100)",
          "primaryKey": false,
          "notNull": false
        },
        "company": {
          "name": "company",
          "type": "text",
          "primaryKey": false,
          "notNull": false
        },
        "hourly_rate": {
          "name": "hourly_rate",
          "type": "integer",
          "primaryKey": false,
          "notNull": false
        },
        "open_to_open_source": {
          "name": "open_to_open_source",
          "type": "boolean",
          "primaryKey": false,
          "notNull": false,
          "default": false
        },
        "available_for_hire": {
          "name": "available_for_hire",
          "type": "boolean",
          "primaryKey": false,
          "notNull": false,
          "default": true
        },
        "services_offered": {
          "name": "services_offered",
          "type": "text",
          "primaryKey": false,
          "notNull": false
        },
        "past_experiences": {
          "name": "past_experiences",
          "type": "text",
          "primaryKey": false,
          "notNull": false
        },
        "portfolio_projects": {
          "name": "portfolio_projects",
          "type": "text",
          "primaryKey": false,
          "notNull": false
        },
        "kyc_status": {
          "name": "kyc_status",
          "type": "varchar(20)",
          "primaryKey": false,
          "notNull": false,
          "default": "'pending'"
        },
        "kyc_submitted_at": {
          "name": "kyc_submitted_at",
          "type": "timestamp",
          "primaryKey": false,
          "notNull": false
        },
        "kyc_verified_at": {
          "name": "kyc_verified_at",
          "type": "timestamp",
          "primaryKey": false,
          "notNull": false
        },
        "kyc_rejected_at": {
          "name": "kyc_rejected_at",
          "type": "timestamp",
          "primaryKey": false,
          "notNull": false
        },
        "kyc_rejection_reason": {
          "name": "kyc_rejection_reason",
          "type": "text",
          "primaryKey": false,
          "notNull": false
        },
        "full_legal_name": {
          "name": "full_legal_name",
          "type": "text",
          "primaryKey": false,
          "notNull": false
        },
        "date_of_birth": {
          "name": "date_of_birth",
          "type": "timestamp",
          "primaryKey": false,
          "notNull": false
        },
        "nationality": {
          "name": "nationality",
          "type": "varchar(100)",
          "primaryKey": false,
          "notNull": false
        },
        "government_id_type": {
          "name": "government_id_type",
          "type": "varchar(50)",
          "primaryKey": false,
          "notNull": false
        },
        "government_id_number": {
          "name": "government_id_number",
          "type": "varchar(100)",
          "primaryKey": false,
          "notNull": false
        },
        "government_id_front_image": {
          "name": "government_id_front_image",
          "type": "text",
          "primaryKey": false,
          "notNull": false
        },
        "government_id_back_image": {
          "name": "government_id_back_image",
          "type": "text",
          "primaryKey": false,
          "notNull": false
        },
        "address_proof_type": {
          "name": "address_proof_type",
          "type": "varchar(50)",
          "primaryKey": false,
          "notNull": false
        },
        "address_proof_image": {
          "name": "address_proof_image",
          "type": "text",
          "primaryKey": false,
          "notNull": false
        },
        "selfie_image": {
          "name": "selfie_image",
          "type": "text",
          "primaryKey": false,
          "notNull": false
        },
        "liveness_video": {
          "name": "liveness_video",
          "type": "text",
          "primaryKey": false,
          "notNull": false
        },
        "kyc_address": {
          "name": "kyc_address",
          "type": "text",
          "primaryKey": false,
          "notNull": false
        },
        "kyc_city": {
          "name": "kyc_city",
          "type": "varchar(100)",
          "primaryKey": false,
          "notNull": false
        },
        "kyc_state": {
          "name": "kyc_state",
          "type": "varchar(100)",
          "primaryKey": false,
          "notNull": false
        },
        "kyc_country": {
          "name": "kyc_country",
          "type": "varchar(100)",
          "primaryKey": false,
          "notNull": false
        },
        "kyc_postal_code": {
          "name": "kyc_postal_code",
          "type": "varchar(20)",
          "primaryKey": false,
          "notNull": false
        },
        "is_email_verified": {
          "name": "is_email_verified",
          "type": "boolean",
          "primaryKey": false,
          "notNull": false,
          "default": false
        },
        "is_phone_verified": {
          "name": "is_phone_verified",
          "type": "boolean",
          "primaryKey": false,
          "notNull": false,
          "default": false
        },
        "is_available": {
          "name": "is_available",
          "type": "boolean",
          "primaryKey": false,
          "notNull": false,
          "default": true
        },
        "status": {
          "name": "status",
          "type": "varchar(20)",
          "primaryKey": false,
          "notNull": false,
          "default": "'active'"
        },
        "block_reason": {
          "name": "block_reason",
          "type": "text",
          "primaryKey": false,
          "notNull": false
        },
        "plan": {
          "name": "plan",
          "type": "varchar(20)",
          "primaryKey": false,
          "notNull": false,
          "default": "'base'"
        },
        "plan_billing_cycle": {
          "name": "plan_billing_cycle",
          "type": "varchar(20)",
          "primaryKey": false,
          "notNull": false,
          "default": "'monthly'"
        },
        "plan_start_date": {
          "name": "plan_start_date",
          "type": "timestamp",
          "primaryKey": false,
          "notNull": false
        },
        "plan_end_date": {
          "name": "plan_end_date",
          "type": "timestamp",
          "primaryKey": false,
          "notNull": false
        },
        "created_at": {
          "name": "created_at",
          "type": "timestamp",
          "primaryKey": false,
          "notNull": false,
          "default": "now()"
        },
        "updated_at": {
          "name": "updated_at",
          "type": "timestamp",
          "primaryKey": false,
          "notNull": false,
          "default": "now()"
        },
        "last_login_at": {
          "name": "last_login_at",
          "type": "timestamp",
          "primaryKey": false,
          "notNull": false
        }
      },
      "indexes": {},
      "foreignKeys": {},
      "compositePrimaryKeys": {},
      "uniqueConstraints": {
        "developers_email_unique": {
          "name": "developers_email_unique",
          "nullsNotDistinct": false,
          "columns": [
            "email"
          ]
        },
        "developers_google_id_unique": {
          "name": "developers_google_id_unique",
          "nullsNotDistinct": false,
          "columns": [
            "google_id"
          ]
        },
        "developers_apple_id_unique": {
          "name": "developers_apple_id_unique",
          "nullsNotDistinct": false,
          "columns": [
            "apple_id"
          ]
        },
        "developers_microsoft_id_unique": {
          "name": "developers_microsoft_id_unique",
          "nullsNotDistinct": false,
          "columns": [
            "microsoft_id"
          ]
        }
      },
      "policies": {},
      "checkConstraints": {},
      "isRLSEnabled": false
    },
    "public.product_categories": {
      "name": "product_categories",
      "schema": "",
      "columns": {
        "id": {
          "name": "id",
          "type": "serial",
          "primaryKey": true,
          "notNull": true
        },
        "name": {
          "name": "name",
          "type": "varchar(80)",
          "primaryKey": false,
          "notNull": true
        },
        "created_at": {
          "name": "created_at",
          "type": "timestamp",
          "primaryKey": false,
          "notNull": false,
          "default": "now()"
        },
        "updated_at": {
          "name": "updated_at",
          "type": "timestamp",
          "primaryKey": false,
          "notNull": false,
          "default": "now()"
        }
      },
      "indexes": {},
      "foreignKeys": {},
      "compositePrimaryKeys": {},
      "uniqueConstraints": {
        "product_categories_name_unique": {
          "name": "product_categories_name_unique",
          "nullsNotDistinct": false,
          "columns": [
            "name"
          ]
        }
      },
      "policies": {},
      "checkConstraints": {},
      "isRLSEnabled": false
    }
  },
  "enums": {},
  "schemas": {},
  "sequences": {},
  "roles": {},
  "policies": {},
  "views": {},
  "_meta": {
    "columns": {},
    "schemas": {},
    "tables": {}
  }
}